kbase/sdk_baseclient.py
kbase_sdk_baseclient-0.1.0.dist-info/METADATA
kbase_sdk_baseclient-0.1.0.dist-info/WHEEL
kbase_sdk_baseclient-0.1.0.dist-info/licenses/LICENSE.md
kbase_sdk_baseclient-0.1.0.dist-info/RECORD
