Metadata-Version: 2.4
Name: kbase-sdk-baseclient
Version: 0.1.0
Summary: Base client for the KBase SDK
Project-URL: Homepage, https://github.com/kbase/kb_sdk_baseclient
Project-URL: Repository, https://github.com/kbase/kb_sdk_baseclient
Project-URL: Issues, https://github.com/kbase/kb_sdk_baseclient/issues
Author: KBase Development Team
License: MIT
License-File: LICENSE.md
Classifier: License :: OSI Approved :: MIT License
Classifier: Operating System :: OS Independent
Classifier: Programming Language :: Python :: 3
Requires-Python: >=3.12
Requires-Dist: requests>=2.32.5
